{"repo": {"timestamp": 1752134394000}, "packages": {"com.noismaster.bambuman": {"metadata": {"lastUpdated": 1752134394000, "icon": {"en-US": {"name": "/icons/com.noismaster.bambuman.123.png"}}}, "versions": {"0e754eee0e649b1d62e2c50ac24424e796b72b4a1c2ce8bc1692954f278344f7": {"added": 1752134394000, "file": {"name": "/com.noismaster.bambuman-1.0.123.apk", "sha256": "0e754eee0e649b1d62e2c50ac24424e796b72b4a1c2ce8bc1692954f278344f7", "size": 51117632}, "manifest": {"nativecode": ["arm64-v8a", "x86_64"], "versionName": "1.0.123", "versionCode": 123, "usesSdk": {"minSdkVersion": 21, "targetSdkVersion": 35}, "signer": {"sha256": ["ab0ac214501ba2259dc95e298ea5fd5a319068d5e51b72747fbca4473c3d96f5"]}, "usesPermission": [{"name": "android.permission.ACCESS_NETWORK_STATE"}, {"name": "android.permission.INTERNET"}, {"name": "android.permission.NFC"}, {"name": "android.permission.CAMERA"}, {"name": "android.permission.VIBRATE"}, {"name": "com.noismaster.bambuman.DYNAMIC_RECEIVER_NOT_EXPORTED_PERMISSION"}]}}, "b7c090c65de5665e41e3e0b3c551d68e22a8ed4e5af92cf2d48c35991bd55ea3": {"added": 1752061080000, "file": {"name": "/com.noismaster.bambuman-1.0.122.apk", "sha256": "b7c090c65de5665e41e3e0b3c551d68e22a8ed4e5af92cf2d48c35991bd55ea3", "size": 51056005}, "manifest": {"nativecode": ["arm64-v8a", "x86_64"], "versionName": "1.0.122", "versionCode": 122, "usesSdk": {"minSdkVersion": 21, "targetSdkVersion": 35}, "signer": {"sha256": ["ab0ac214501ba2259dc95e298ea5fd5a319068d5e51b72747fbca4473c3d96f5"]}, "usesPermission": [{"name": "android.permission.ACCESS_NETWORK_STATE"}, {"name": "android.permission.INTERNET"}, {"name": "android.permission.NFC"}, {"name": "android.permission.CAMERA"}, {"name": "android.permission.VIBRATE"}, {"name": "com.noismaster.bambuman.DYNAMIC_RECEIVER_NOT_EXPORTED_PERMISSION"}]}}}}}}